shellmind/__init__.py
shellmind/ai_handler.py
shellmind/cli.py
shellmind/utils.py
shellmind-0.2.5.dist-info/licenses/LICENSE
shellmind-0.2.5.dist-info/METADATA
shellmind-0.2.5.dist-info/WHEEL
shellmind-0.2.5.dist-info/entry_points.txt
shellmind-0.2.5.dist-info/top_level.txt
shellmind-0.2.5.dist-info/RECORD
