Metadata-Version: 2.4
Name: shellmind
Version: 0.2.5
Summary: AI-powered terminal assistant for generating, understanding, and executing command-line instructions.
Author-email: Karl Danisz <k@mktr.sbs>
License: MIT License
Project-URL: Homepage, https://github.com/k-mktr/shellmind
Project-URL: Documentation, https://github.com/k-mktr/shellmind#readme
Project-URL: Repository, https://github.com/k-mktr/shellmind
Project-URL: Issues, https://github.com/k-mktr/shellmind/issues
Project-URL: Changelog, https://github.com/k-mktr/shellmind/blob/main/CHANGELOG.md
Keywords: terminal,cli,ai,shell,command-line,linux
Classifier: Development Status :: 4 - Beta
Classifier: Intended Audience :: Developers
Classifier: Intended Audience :: System Administrators
Classifier: License :: OSI Approved :: MIT License
Classifier: Operating System :: POSIX :: Linux
Classifier: Programming Language :: Python :: 3
Classifier: Programming Language :: Python :: 3.9
Classifier: Programming Language :: Python :: 3.10
Classifier: Programming Language :: Python :: 3.11
Classifier: Programming Language :: Python :: 3.12
Classifier: Programming Language :: Python :: 3.13
Classifier: Topic :: Utilities
Classifier: Topic :: System :: Shells
Requires-Python: >=3.9
License-File: LICENSE
Requires-Dist: openai>=1.61.1
Requires-Dist: python-dotenv>=0.21.0
Requires-Dist: argparse>=1.4.0
Provides-Extra: ollama
Requires-Dist: ollama>=0.5.7; extra == "ollama"
Dynamic: license-file
